pysra/__init__.py
pysra/motion.py
pysra/output.py
pysra/propagation.py
pysra/site.py
pysra/tools.py
pysra/variation.py
tests/__init__.py
tests/test_motion.py
tests/test_notebooks.py
tests/test_output.py
tests/test_propagation.py
tests/test_site.py
tests/test_variation.py
pySRA-0.5.0.dist-info/AUTHORS.rst
pySRA-0.5.0.dist-info/LICENSE
pySRA-0.5.0.dist-info/METADATA
pySRA-0.5.0.dist-info/WHEEL
pySRA-0.5.0.dist-info/top_level.txt
pySRA-0.5.0.dist-info/RECORD
