Metadata-Version: 2.1
Name: pySRA
Version: 0.5.0
Summary: Site Response Analysis with Python
Home-page: http://github.com/arkottke/pysra
Author: Albert Kottke
Author-email: albert.kottke@gmail.com
License: MIT
Keywords: site response
Classifier: Development Status :: 4 - Beta
Classifier: Environment :: Console
Classifier: License :: OSI Approved :: MIT License
Classifier: Natural Language :: English
Classifier: Operating System :: OS Independent
Classifier: Programming Language :: Python
Classifier: Programming Language :: Python :: 3.6
Classifier: Topic :: Scientific/Engineering
Classifier: Intended Audience :: Science/Research
License-File: LICENSE
License-File: AUTHORS.rst
Requires-Dist: pystrata
Requires-Dist: matplotlib
Requires-Dist: numpy
Requires-Dist: pyrvt
Requires-Dist: pykooh
Requires-Dist: scipy
Requires-Dist: setuptools
Requires-Dist: typing
Provides-Extra: dataframe
Requires-Dist: pandas ; extra == 'dataframe'
